MANIFEST.in
setup.py
orbited2/__init__.py
orbited2/config.py
orbited2/protocol.py
orbited2/server.py
orbited2/start.py
orbited2.egg-info/PKG-INFO
orbited2.egg-info/SOURCES.txt
orbited2.egg-info/dependency_links.txt
orbited2.egg-info/entry_points.txt
orbited2.egg-info/not-zip-safe
orbited2.egg-info/requires.txt
orbited2.egg-info/top_level.txt
orbited2/admin/__init__.py
orbited2/js_src/Orbited2.js
orbited2/static/Orbited2.js
orbited2/static/Orbited2.min.js