Metadata-Version: 1.0
Name: orbited2
Version: 2.0.a3
Summary: A WebSocket-enabling proxy, so you can code against Websocket in any browser.
Home-page: http://www.github.com/mcarter/orbited2
Author: Michael Carter
Author-email: CarterMichael@gmail.com
License: MIT License
Platform: UNKNOWN
Classifier: Development Status :: 4 - Beta
Classifier: Environment :: Console
Classifier: Intended Audience :: Developers
Classifier: License :: OSI Approved :: MIT License
Classifier: Operating System :: OS Independent
Classifier: Programming Language :: Python
Classifier: Topic :: Software Development :: Libraries :: Python Modules
